pynamo/__init__.py
pynamo/test/__init__.py
pynamo/test/test_dynamo.py
pynamo-1.2.1539718609.dist-info/DESCRIPTION.rst
pynamo-1.2.1539718609.dist-info/METADATA
pynamo-1.2.1539718609.dist-info/RECORD
pynamo-1.2.1539718609.dist-info/WHEEL
pynamo-1.2.1539718609.dist-info/metadata.json
pynamo-1.2.1539718609.dist-info/top_level.txt
