Metadata-Version: 2.0
Name: pynamo
Version: 1.2.1539718609
Summary: Python Library for Handling Dynamo Syntax and requests.
Home-page: https://github.build.ge.com/Cloudpod/pynamo
Author: Barry Howard
Author-email: barry.howard@ge.com
License: UNKNOWN
Keywords: dynamo,ge,cloudops,aws
Platform: UNKNOWN
